{
    "0": {
        "match_id": "vxmstlikwteawcnm95897",
        "match_date": "25.02. 12:30",
        "start_time": "",
        "end_time": "",
        "name": "Alaves-Mallorca",
        "home": "Alaves",
        "visitor": "Mallorca",
        "home_result": "-",
        "visitor_result": "-",
        "link_details": "https://www.flashscore.com/match/f79rmqVM/#/match-summary/match-summary",
        "place": ""
    },
    "1": {
        "match_id": "yqgsvkfgtdxlhaim99964",
        "match_date": "25.02. 12:30",
        "start_time": "",
        "end_time": "",
        "name": "Almeria-Atl. Madrid",
        "home": "Almeria",
        "visitor": "Atl. Madrid",
        "home_result": "-",
        "visitor_result": "-",
        "link_details": "https://www.flashscore.com/match/U5Z9YqGT/#/match-summary/match-summary",
        "place": ""
    },
    "2": {
        "match_id": "bzqorissotfjstvw94314",
        "match_date": "25.02. 12:30",
        "start_time": "",
        "end_time": "",
        "name": "Barcelona-Getafe",
        "home": "Barcelona",
        "visitor": "Getafe",
        "home_result": "-",
        "visitor_result": "-",
        "link_details": "https://www.flashscore.com/match/WELyU3Op/#/match-summary/match-summary",
        "place": ""
    },
    "3": {
        "match_id": "knonlxfbverwlpia94239",
        "match_date": "25.02. 12:30",
        "start_time": "",
        "end_time": "",
        "name": "Betis-Ath Bilbao",
        "home": "Betis",
        "visitor": "Ath Bilbao",
        "home_result": "-",
        "visitor_result": "-",
        "link_details": "https://www.flashscore.com/match/8ADnn3pT/#/match-summary/match-summary",
        "place": ""
    },
    "4": {
        "match_id": "gloidnhccmleqfei02456",
        "match_date": "25.02. 12:30",
        "start_time": "",
        "end_time": "",
        "name": "Cadiz CF-Celta Vigo",
        "home": "Cadiz CF",
        "visitor": "Celta Vigo",
        "home_result": "-",
        "visitor_result": "-",
        "link_details": "https://www.flashscore.com/match/pI9Jhm1o/#/match-summary/match-summary",
        "place": ""
    },
    "5": {
        "match_id": "bcltskpswewlnazd93792",
        "match_date": "25.02. 12:30",
        "start_time": "",
        "end_time": "",
        "name": "Girona-Rayo Vallecano",
        "home": "Girona",
        "visitor": "Rayo Vallecano",
        "home_result": "-",
        "visitor_result": "-",
        "link_details": "https://www.flashscore.com/match/r3SMi7Gi/#/match-summary/match-summary",
        "place": ""
    },
    "6": {
        "match_id": "cguczlnzxvxymqrr99529",
        "match_date": "25.02. 12:30",
        "start_time": "",
        "end_time": "",
        "name": "Granada CF-Valencia",
        "home": "Granada CF",
        "visitor": "Valencia",
        "home_result": "-",
        "visitor_result": "-",
        "link_details": "https://www.flashscore.com/match/YiLZl50A/#/match-summary/match-summary",
        "place": ""
    },
    "7": {
        "match_id": "phwdoimqcxguiipv95582",
        "match_date": "25.02. 12:30",
        "start_time": "",
        "end_time": "",
        "name": "Las Palmas-Osasuna",
        "home": "Las Palmas",
        "visitor": "Osasuna",
        "home_result": "-",
        "visitor_result": "-",
        "link_details": "https://www.flashscore.com/match/CrKwlPFG/#/match-summary/match-summary",
        "place": ""
    },
    "8": {
        "match_id": "mqtcblxvxtyigdth05553",
        "match_date": "25.02. 12:30",
        "start_time": "",
        "end_time": "",
        "name": "Real Madrid-Sevilla",
        "home": "Real Madrid",
        "visitor": "Sevilla",
        "home_result": "-",
        "visitor_result": "-",
        "link_details": "https://www.flashscore.com/match/QRHRjRVc/#/match-summary/match-summary",
        "place": ""
    },
    "9": {
        "match_id": "vnzfeznawlpxeeyx98605",
        "match_date": "25.02. 12:30",
        "start_time": "",
        "end_time": "",
        "name": "Real Sociedad-Villarreal",
        "home": "Real Sociedad",
        "visitor": "Villarreal",
        "home_result": "-",
        "visitor_result": "-",
        "link_details": "https://www.flashscore.com/match/4IGVkoo4/#/match-summary/match-summary",
        "place": ""
    }
}